tinyloggy/__init__.py
tinnyloggy-0.1.0.dist-info/METADATA
tinnyloggy-0.1.0.dist-info/WHEEL
tinnyloggy-0.1.0.dist-info/top_level.txt
tinnyloggy-0.1.0.dist-info/RECORD
