Metadata-Version: 2.4
Name: tinnyloggy
Version: 0.1.0
Summary: Lightweight terminal logger with timestamps and optional caller inspection.
Home-page: https://github.com/yourusername/loggerx
Author: Aydyn Maxadov
Classifier: Programming Language :: Python :: 3
Classifier: License :: OSI Approved :: MIT License
Classifier: Operating System :: OS Independent
Requires-Python: >=3.6
Requires-Dist: colorama
Dynamic: author
Dynamic: classifier
Dynamic: description
Dynamic: description-content-type
Dynamic: home-page
Dynamic: requires-dist
Dynamic: requires-python
Dynamic: summary
